amfiprot/__init__.py
amfiprot/common_payload.py
amfiprot/configurator.py
amfiprot/connection.py
amfiprot/device.py
amfiprot/node.py
amfiprot/packet.py
amfiprot/payload.py
amfiprot/response_payload.py
amfiprot/uart_connection.py
amfiprot/usb_connection.py
amfiprot-0.1.14.dist-info/licenses/LICENSE
amfiprot-0.1.14.dist-info/METADATA
amfiprot-0.1.14.dist-info/WHEEL
amfiprot-0.1.14.dist-info/top_level.txt
amfiprot-0.1.14.dist-info/RECORD
