Metadata-Version: 2.4
Name: amfiprot
Version: 0.1.14
Summary: Core library for Amfiprot
Author: Kristian Klein-Wengel
Author-email: kkw@amfitech.dk
Classifier: Programming Language :: Python :: 3
Classifier: License :: OSI Approved :: MIT License
Classifier: Operating System :: Microsoft :: Windows :: Windows 10
Requires-Python: >=3.7
License-File: LICENSE
Requires-Dist: crcmod
Requires-Dist: pyusb
Requires-Dist: libusb_package
Requires-Dist: cobs
Requires-Dist: pyserial
Dynamic: license-file
